static_precompiler/__init__.py
static_precompiler/caching.py
static_precompiler/exceptions.py
static_precompiler/finders.py
static_precompiler/models.py
static_precompiler/mtime.py
static_precompiler/mypy_django_settings.py
static_precompiler/py.typed
static_precompiler/registry.py
static_precompiler/settings.py
static_precompiler/types.py
static_precompiler/url_converter.py
static_precompiler/utils.py
static_precompiler/watch.py
static_precompiler/compilers/__init__.py
static_precompiler/compilers/babel.py
static_precompiler/compilers/base.py
static_precompiler/compilers/coffeescript.py
static_precompiler/compilers/dart_sass.py
static_precompiler/compilers/handlebars.py
static_precompiler/compilers/less.py
static_precompiler/compilers/libsass.py
static_precompiler/compilers/livescript.py
static_precompiler/compilers/ruby_scss.py
static_precompiler/compilers/scss.py
static_precompiler/compilers/stylus.py
static_precompiler/management/__init__.py
static_precompiler/management/commands/__init__.py
static_precompiler/management/commands/compilestatic.py
static_precompiler/migrations/0001_initial.py
static_precompiler/migrations/__init__.py
static_precompiler/templatetags/__init__.py
static_precompiler/templatetags/compile_static.py
django_static_precompiler-2.4.dist-info/AUTHORS
django_static_precompiler-2.4.dist-info/LICENSE
django_static_precompiler-2.4.dist-info/METADATA
django_static_precompiler-2.4.dist-info/WHEEL
django_static_precompiler-2.4.dist-info/top_level.txt
django_static_precompiler-2.4.dist-info/RECORD
