Metadata-Version: 2.1
Name: django-static-precompiler
Version: 2.4
Summary: Django template tags to compile all kinds of static files
Home-page: https://github.com/andreyfedoseev/django-static-precompiler
Author: Andrey Fedoseev
Author-email: andrey@andreyfedoseev.com
Project-URL: Bug Tracker, https://github.com/andreyfedoseev/django-static-precompiler/issues/
Project-URL: Repository, https://github.com/andreyfedoseev/django-static-precompiler
Project-URL: Documentation, https://django-static-precompiler.readthedocs.io/
Keywords: sass,scss,less,stylus,css,coffeescript,javascript,babel,livescript,handlebars
Classifier: Development Status :: 5 - Production/Stable
Classifier: Framework :: Django :: 2
Classifier: Framework :: Django :: 3
Classifier: Framework :: Django :: 4
Classifier: Intended Audience :: Developers
Classifier: License :: OSI Approved :: BSD License
Classifier: Operating System :: OS Independent
Classifier: Programming Language :: Python :: 3.6
Classifier: Programming Language :: Python :: 3.7
Classifier: Programming Language :: Python :: 3.8
Classifier: Programming Language :: Python :: 3.9
Classifier: Programming Language :: Python :: 3.10
Classifier: Programming Language :: Python :: 3.11
Classifier: Topic :: Internet :: WWW/HTTP
Requires-Python: >=3.6
Provides-Extra: watch
Provides-Extra: libsass
License-File: LICENSE
License-File: AUTHORS
